mlrunner/__init__.py
mlrunner/run.py
mlrunner/examine/__init__.py
mlrunner/examine/examiner.py
mlrunner/utils/__init__.py
mlrunner/utils/config.py
mlrunner/utils/misc.py
mlrunner-0.5.9.dist-info/LICENSE
mlrunner-0.5.9.dist-info/METADATA
mlrunner-0.5.9.dist-info/WHEEL
mlrunner-0.5.9.dist-info/entry_points.txt
mlrunner-0.5.9.dist-info/top_level.txt
mlrunner-0.5.9.dist-info/RECORD
