Metadata-Version: 2.1
Name: mlrunner
Version: 0.5.9
Summary: A light-weight script for maintaining a LOT of machine learning experiments.
Home-page: https://github.com/simtony/mlrunner
Author: Tony Ou
Author-email: simtony2@gmail.com
Classifier: Programming Language :: Python :: 3
Classifier: License :: OSI Approved :: MIT License
Classifier: Operating System :: POSIX :: Linux
Requires-Python: >=3.7
License-File: LICENSE
Requires-Dist: pyyaml
Requires-Dist: tabulate
Requires-Dist: ilock
Requires-Dist: pandas
Requires-Dist: dill (==0.3.6)
Requires-Dist: multiprocess (==0.70.14)
